{
  "data": {
    "id": "f3a5b1c8-2d4e-4f60-8192-a3b4c5d6e7f8",
    "kind": "event",
    "event_type": "incident_event.created",
    "event": "Investigation started; rolling back snaketoy-web to 1.4.1",
    "event_raw": "Investigation started; rolling back snaketoy-web to 1.4.1",
    "event_id": "b3065ca8-69a6-4781-b6b4-94d6f0317ccf",
    "incident_id": "8a4f7b3c-1d2e-4f60-8192-a3b4c5d6e7f8",
    "incident": {
      "id": "8a4f7b3c-1d2e-4f60-8192-a3b4c5d6e7f8",
      "title": "snaketoy-web 5xx spike (eu-west-1)",
      "status": "mitigated",
      "severity": "sev2",
      "services": [
        "snaketoy-web"
      ],
      "teams": [
        "platform"
      ]
    },
    "source": "web",
    "visibility": "internal",
    "created_at": "2026-03-04T09:21:18.412-08:00",
    "updated_at": "2026-03-04T09:21:18.412-08:00",
    "occurred_at": "2026-03-04T09:21:18.412-08:00",
    "issued_at": "2026-03-04T09:21:18.612-08:00"
  },
  "timestamp": "2026-03-04T17:21:18.812Z",
  "type": "rootly.onIncidentTimelineEvent"
}
